config/fd3.cfg
config/lmd.cfg
config/metropro.cfg
hexer/__init__.py
hexer/hexer.py
hexer/metropro.py
hexer/config/bruker_opus.cfg
hexer/config/fd3.cfg
hexer/config/lmd.cfg
hexer/config/metropro.cfg
hexer-0.0.2.dist-info/DESCRIPTION.rst
hexer-0.0.2.dist-info/METADATA
hexer-0.0.2.dist-info/RECORD
hexer-0.0.2.dist-info/WHEEL
hexer-0.0.2.dist-info/metadata.json
hexer-0.0.2.dist-info/top_level.txt
tests/__init__.py
tests/test_blocks.py
tests/test_bruker_opus.py
tests/test_chunks.py
tests/test_fd3.py
tests/test_hexdump.py
tests/test_lmd.py
tests/test_metropro.py
tests/test_strings.py
