Metadata-Version: 2.0
Name: hexer
Version: 0.0.2
Summary: binary file description
Home-page: https://bitbucket.org/hirschbeutel/
Author: hirschbeutel
Author-email: hirschbeutel@gmail.com
License: MIT
Platform: UNKNOWN
